MANIFEST.in
README
README.md
setup.py
test.py
python_pid/__init__.py
python_pid.egg-info/PKG-INFO
python_pid.egg-info/SOURCES.txt
python_pid.egg-info/dependency_links.txt
python_pid.egg-info/top_level.txt